GOSTrocks/__init__.py
GOSTrocks/dataMisc.py
GOSTrocks/fathom_vrts.txt
GOSTrocks/ghslMisc.py
GOSTrocks/mapMisc.py
GOSTrocks/misc.py
GOSTrocks/ntlMisc.py
GOSTrocks/osmMisc.py
GOSTrocks/rasterMisc.py
GOSTrocks/shapeMisc.py
gostrocks-1.0.0.dist-info/licenses/LICENSE
gostrocks-1.0.0.dist-info/METADATA
gostrocks-1.0.0.dist-info/WHEEL
gostrocks-1.0.0.dist-info/top_level.txt
gostrocks-1.0.0.dist-info/RECORD
