Metadata-Version: 2.4
Name: GOSTrocks
Version: 1.0.0
Summary: Miscellaneous geospatial functions concerning vector, raster, and network analysis
Author-email: "Benjamin P. Stewart" <ben.gis.stewart@gmail.com>, Andres Chamorro <afche18@gmail.com>
License: Mozilla Public License Version 2.0
Project-URL: Homepage, https://github.com/worldbank/GOSTrocks
Project-URL: Bug Reports, https://github.com/worldbank/GOSTrocks/issues
Project-URL: Source, https://github.com/worldbank/GOSTrocks
Keywords: gostrocks,raster,GOST
Classifier: Programming Language :: Python :: 3.8
Classifier: Programming Language :: Python :: 3.9
Classifier: Programming Language :: Python :: 3.10
Classifier: Programming Language :: Python :: 3.11
Classifier: Programming Language :: Python :: 3 :: Only
Classifier: License :: OSI Approved :: Mozilla Public License 2.0 (MPL 2.0)
Classifier: Operating System :: OS Independent
Classifier: Intended Audience :: Developers
Classifier: Topic :: Scientific/Engineering
Requires-Python: >=3.8
License-File: LICENSE
Requires-Dist: affine
Requires-Dist: boto3
Requires-Dist: botocore
Requires-Dist: contextily
Requires-Dist: click
Requires-Dist: coverage
Requires-Dist: geopandas
Requires-Dist: matplotlib
Requires-Dist: numexpr>=2.6.8
Requires-Dist: numpy
Requires-Dist: osmnx
Requires-Dist: pandas
Requires-Dist: pyproj
Requires-Dist: PyOpenSSL>=23.2
Requires-Dist: python-dotenv>=0.5.1
Requires-Dist: pycountry
Requires-Dist: rasterio
Requires-Dist: s3fs
Requires-Dist: scipy
Requires-Dist: seaborn
Requires-Dist: tqdm
Requires-Dist: xarray
Provides-Extra: dev
Requires-Dist: docutils>=0.21.2; extra == "dev"
Requires-Dist: jupyter-book>=1; extra == "dev"
Requires-Dist: sphinx; extra == "dev"
Requires-Dist: iPython; extra == "dev"
Requires-Dist: standard-imghdr; extra == "dev"
Requires-Dist: sphinxcontrib-apidoc; extra == "dev"
Requires-Dist: pytest; extra == "dev"
Dynamic: license-file
